{
  "version": 1,
  "runs": [
    {
      "timestamp": "2026-04-19T16:35:31",
      "filepath": "<test>",
      "language": "python",
      "loc": 3,
      "loc_bucket": "0-20 LOC",
      "statement_count": 3,
      "function_count": 0,
      "cyclomatic_complexity": 2,
      "max_nesting_depth": 1,
      "complexity_rating": "low",
      "cfg_blocks": 5,
      "cfg_edges": 2,
      "tac_instructions": 16,
      "loops_detected": 1,
      "branches_detected": 2,
      "unreachable_blocks": 0,
      "error_count": 3,
      "parse_time_ms": 6.5366,
      "ir_build_time_ms": 0.1091,
      "analysis_pass_ms": 0.1205,
      "total_analysis_ms": 6.7749,
      "estimated_energy_mj": 1.3044,
      "throughput_loc_per_s": 442.811,
      "useful_work_units": 8.9493,
      "efficiency_score": 63.1704,
      "run_number": 1,
      "cumulative_energy_mj": 1.3044
    },
    {
      "timestamp": "2026-04-19T16:36:02",
      "filepath": "<editor>",
      "language": "python",
      "loc": 10,
      "loc_bucket": "0-20 LOC",
      "statement_count": 8,
      "function_count": 2,
      "cyclomatic_complexity": 5,
      "max_nesting_depth": 3,
      "complexity_rating": "low",
      "cfg_blocks": 4,
      "cfg_edges": 2,
      "tac_instructions": 9,
      "loops_detected": 0,
      "branches_detected": 1,
      "unreachable_blocks": 0,
      "error_count": 5,
      "parse_time_ms": 0.2701,
      "ir_build_time_ms": 0.0439,
      "analysis_pass_ms": 0.1095,
      "total_analysis_ms": 0.4306,
      "estimated_energy_mj": 1.5244,
      "throughput_loc_per_s": 23223.4082,
      "useful_work_units": 13.5775,
      "efficiency_score": 69.0085,
      "run_number": 2,
      "cumulative_energy_mj": 2.8288
    },
    {
      "timestamp": "2026-04-19T16:38:48",
      "filepath": "<editor>",
      "language": "python",
      "loc": 41,
      "loc_bucket": "20-50 LOC",
      "statement_count": 36,
      "function_count": 5,
      "cyclomatic_complexity": 241,
      "max_nesting_depth": 10,
      "complexity_rating": "very_high",
      "cfg_blocks": 5,
      "cfg_edges": 3,
      "tac_instructions": 9,
      "loops_detected": 1,
      "branches_detected": 6,
      "unreachable_blocks": 0,
      "error_count": 9,
      "parse_time_ms": 1.1277,
      "ir_build_time_ms": 0.0397,
      "analysis_pass_ms": 0.2617,
      "total_analysis_ms": 1.4424,
      "estimated_energy_mj": 45.2128,
      "throughput_loc_per_s": 28424.8478,
      "useful_work_units": 6.1003,
      "efficiency_score": 3.263,
      "run_number": 3,
      "cumulative_energy_mj": 48.0416
    },
    {
      "timestamp": "2026-04-19T16:40:52",
      "filepath": "<editor>",
      "language": "python",
      "loc": 93,
      "loc_bucket": "51-100 LOC",
      "statement_count": 85,
      "function_count": 8,
      "cyclomatic_complexity": 6145,
      "max_nesting_depth": 22,
      "complexity_rating": "very_high",
      "cfg_blocks": 5,
      "cfg_edges": 3,
      "tac_instructions": 9,
      "loops_detected": 2,
      "branches_detected": 16,
      "unreachable_blocks": 0,
      "error_count": 8,
      "parse_time_ms": 2.1166,
      "ir_build_time_ms": 0.0296,
      "analysis_pass_ms": 0.4421,
      "total_analysis_ms": 2.5949,
      "estimated_energy_mj": 1109.5616,
      "throughput_loc_per_s": 35839.531,
      "useful_work_units": 0.603,
      "efficiency_score": 0.0136,
      "run_number": 4,
      "cumulative_energy_mj": 1157.6032
    },
    {
      "timestamp": "2026-04-19T16:51:56",
      "filepath": "<editor>",
      "language": "python",
      "loc": 129,
      "loc_bucket": "101-200 LOC",
      "statement_count": 122,
      "function_count": 7,
      "cyclomatic_complexity": 4865,
      "max_nesting_depth": 28,
      "complexity_rating": "very_high",
      "cfg_blocks": 5,
      "cfg_edges": 3,
      "tac_instructions": 9,
      "loops_detected": 3,
      "branches_detected": 24,
      "unreachable_blocks": 0,
      "error_count": 8,
      "parse_time_ms": 3.3926,
      "ir_build_time_ms": 0.0474,
      "analysis_pass_ms": 0.6947,
      "total_analysis_ms": 4.145,
      "estimated_energy_mj": 880.5255,
      "throughput_loc_per_s": 31121.8334,
      "useful_work_units": 1.0096,
      "efficiency_score": 0.0287,
      "run_number": 5,
      "cumulative_energy_mj": 2038.1287
    },
    {
      "timestamp": "2026-04-19T16:55:58",
      "filepath": "<editor>",
      "language": "python",
      "loc": 236,
      "loc_bucket": "200-500 LOC",
      "statement_count": 229,
      "function_count": 7,
      "cyclomatic_complexity": 8065,
      "max_nesting_depth": 45,
      "complexity_rating": "very_high",
      "cfg_blocks": 5,
      "cfg_edges": 3,
      "tac_instructions": 9,
      "loops_detected": 8,
      "branches_detected": 46,
      "unreachable_blocks": 0,
      "error_count": 7,
      "parse_time_ms": 6.9052,
      "ir_build_time_ms": 0.0355,
      "analysis_pass_ms": 1.2772,
      "total_analysis_ms": 8.2302,
      "estimated_energy_mj": 1460.5357,
      "throughput_loc_per_s": 28674.8804,
      "useful_work_units": 1.0787,
      "efficiency_score": 0.0185,
      "run_number": 6,
      "cumulative_energy_mj": 3498.6644
    },
    {
      "timestamp": "2026-04-19T17:10:37",
      "filepath": "<editor>",
      "language": "python",
      "loc": 10,
      "loc_bucket": "0-20 LOC",
      "statement_count": 8,
      "function_count": 2,
      "cyclomatic_complexity": 5,
      "max_nesting_depth": 3,
      "complexity_rating": "low",
      "cfg_blocks": 4,
      "cfg_edges": 2,
      "tac_instructions": 9,
      "loops_detected": 0,
      "branches_detected": 1,
      "unreachable_blocks": 0,
      "error_count": 5,
      "parse_time_ms": 0.2926,
      "ir_build_time_ms": 0.0446,
      "analysis_pass_ms": 0.1093,
      "total_analysis_ms": 0.4539,
      "estimated_energy_mj": 1.5252,
      "throughput_loc_per_s": 22031.2862,
      "useful_work_units": 13.5775,
      "efficiency_score": 68.9973,
      "run_number": 7,
      "cumulative_energy_mj": 3500.1896
    }
  ]
}